gmocoin_backtest/__init__.py
gmocoin_backtest/gmocoin_backtest.py
gmocoin_backtest-0.1.2.dist-info/LICENSE.txt
gmocoin_backtest-0.1.2.dist-info/METADATA
gmocoin_backtest-0.1.2.dist-info/WHEEL
gmocoin_backtest-0.1.2.dist-info/top_level.txt
gmocoin_backtest-0.1.2.dist-info/RECORD
