Metadata-Version: 2.1
Name: gmocoin-backtest
Version: 0.1.2
Summary: gmocoin-backtest is a python library         for backtest with gmocoin fx btc trade technical             analysis on Python 3.7 and above.
Home-page: https://github.com/10mohi6/gmocoin-backtest-python
Author: 10mohi6
Author-email: 10.mohi.6.y@gmail.com
License: MIT
Keywords: gmocoin trade python backtest fx strategy technical analysis jpy btc
Platform: UNKNOWN
Classifier: Development Status :: 4 - Beta
Classifier: Programming Language :: Python
Classifier: Programming Language :: Python :: 3
Classifier: Programming Language :: Python :: 3.7
Classifier: Programming Language :: Python :: 3.8
Classifier: Programming Language :: Python :: 3.9
Classifier: Intended Audience :: Developers
Classifier: Intended Audience :: Financial and Insurance Industry
Classifier: Operating System :: OS Independent
Classifier: Topic :: Office/Business :: Financial :: Investment
Classifier: License :: OSI Approved :: MIT License
Requires-Python: >=3.7.0
Requires-Dist: requests
Requires-Dist: numpy
Requires-Dist: pandas
Requires-Dist: matplotlib
Requires-Dist: beautifulsoup4
Requires-Dist: SQLAlchemy
Requires-Dist: lxml
